pydlm/__init__.py
pydlm/dlm.py
pydlm/access/__init__.py
pydlm/access/_dlmGet.py
pydlm/access/dlmAccessMod.py
pydlm/base/__init__.py
pydlm/base/baseModel.py
pydlm/base/kalmanFilter.py
pydlm/base/tools.py
pydlm/core/__init__.py
pydlm/core/_dlm.py
pydlm/modeler/__init__.py
pydlm/modeler/autoReg.py
pydlm/modeler/builder.py
pydlm/modeler/component.py
pydlm/modeler/dynamic.py
pydlm/modeler/longSeason.py
pydlm/modeler/matrixTools.py
pydlm/modeler/seasonality.py
pydlm/modeler/trends.py
pydlm/plot/__init__.py
pydlm/plot/dlmPlot.py
pydlm/plot/dlmPlotMod.py
pydlm/predict/__init__.py
pydlm/predict/_dlmPredict.py
pydlm/predict/dlmPredictMod.py
pydlm/tuner/__init__.py
pydlm/tuner/_dlmTune.py
pydlm/tuner/dlmTuneMod.py
pydlm/tuner/dlmTuner.py
tests/__init__.py
tests/testDlm.py
tests/base/__init__.py
tests/base/testKalmanFilter.py
tests/core/__init__.py
tests/core/test_dlm.py
tests/modeler/__init__.py
tests/modeler/testAutoReg.py
tests/modeler/testBuilder.py
tests/modeler/testDynamic.py
tests/modeler/testLongSeason.py
tests/modeler/testSeasonality.py
tests/modeler/testTrends.py
tests/predict/__init__.py
tests/predict/test_dlmPredict.py
pydlm-0.1.1.13.dist-info/LICENSE
pydlm-0.1.1.13.dist-info/METADATA
pydlm-0.1.1.13.dist-info/WHEEL
pydlm-0.1.1.13.dist-info/top_level.txt
pydlm-0.1.1.13.dist-info/RECORD
