Metadata-Version: 2.1
Name: pydlm
Version: 0.1.1.13
Summary: A python library for the Bayesian dynamic linear model for time series modeling
Home-page: https://github.com/wwrechard/pydlm
Author: Xiangyu Wang
Author-email: wwrechard@gmail.com
License: BSD
Keywords: dlm bayes bayesian kalman filter smoothing dynamic model
Classifier: Development Status :: 3 - Alpha
Classifier: Intended Audience :: Science/Research
Classifier: License :: OSI Approved :: BSD License
Classifier: Operating System :: OS Independent
Classifier: Programming Language :: Python
Classifier: Programming Language :: Python :: 3
Classifier: Topic :: Scientific/Engineering :: Artificial Intelligence
License-File: LICENSE
Requires-Dist: numpy
Requires-Dist: matplotlib
Provides-Extra: docs
Requires-Dist: Sphinx ; extra == 'docs'
